setup.py
Code/__init__.py
pyvtl.egg-info/PKG-INFO
pyvtl.egg-info/SOURCES.txt
pyvtl.egg-info/dependency_links.txt
pyvtl.egg-info/top_level.txt